[   {
"description":"Story",
"title":"Book",
"username":"free_kk",
"banner":"https://th.bing.com/th/id/OIP.DFo68kdWnv4fI1PJoDOjmQHaKh?w=128&h=183&c=7&r=0&o=5&dpr=1.3&pid=1.7"
},
{
"description":"Story1",
"title":"Book2",
"username":"free_kk2",
"banner":"https://th.bing.com/th/id/OIP.DFo68kdWnv4fI1PJoDOjmQHaKh?w=128&h=183&c=7&r=0&o=5&dpr=1.3&pid=1.7"
},
    {
        "description": "Stor44y8",
        "title": "Bo41ok2",
        "username": "fr11ee_kk2",
        "banner": "https://th.bing.com/th/id/OIP.DFo68kdWnv4fI1PJoDOjmQHaKh?w=128&h=183&c=7&r=0&o=5&dpr=1.3&pid=1.7"
    }
]